cbz_merger/cli.py
cbz_merger-0.1.1.dist-info/METADATA
cbz_merger-0.1.1.dist-info/WHEEL
cbz_merger-0.1.1.dist-info/entry_points.txt
cbz_merger-0.1.1.dist-info/RECORD
