Metadata-Version: 2.4
Name: cbz_merger
Version: 0.1.1
Summary: Merges multiple CBZ/CBR files into one
Author-email: Jury Razumau <mail@razumau.net>
License-Expression: MIT
Requires-Dist: build>=1.2.2.post1
Requires-Dist: rarfile>=4.2
